adaptdl_cli/__init__.py
adaptdl_cli/proxy.py
adaptdl_cli/pvc.py
adaptdl_cli/tensorboard.py
adaptdl_cli-0.2.11.data/scripts/adaptdl
adaptdl_cli-0.2.11.dist-info/METADATA
adaptdl_cli-0.2.11.dist-info/WHEEL
adaptdl_cli-0.2.11.dist-info/top_level.txt
adaptdl_cli-0.2.11.dist-info/RECORD
