Metadata-Version: 2.1
Name: adaptdl-cli
Version: 0.2.11
Summary: Dynamic-resource trainer and scheduler for deep learning
Home-page: https://github.com/petuum/adaptdl
Author: Petuum Inc. & The AdaptDL Authors
Author-email: aurick.qiao@petuum.com
License: UNKNOWN
Platform: UNKNOWN
Classifier: Programming Language :: Python :: 3
Classifier: License :: Other/Proprietary License
Classifier: Operating System :: POSIX :: Linux
Requires-Python: >=3.6
Requires-Dist: kubernetes (>=9.0.0)
Requires-Dist: python-dateutil (>=2.7.3)
Requires-Dist: mitmproxy (>=5.2)
Requires-Dist: portpicker (>=1.3)
